{
  "timestamp": "2025-10-07T09:45:13.777122Z",
  "pixel": {
    "slow": 685,
    "fast": 1039
  },
  "config": "supervisor",
  "device": "cpu",
  "dtype": "float32",
  "per_phi_entries": [
    {
      "phi_tic": 0,
      "phi_deg": 0.0,
      "k_frac": -0.589141607284546,
      "F_latt_b": -0.861241281032562,
      "F_latt": 1.35136013608642
    },
    {
      "phi_tic": 1,
      "phi_deg": 0.0111111111111111,
      "k_frac": -0.591151714324951,
      "F_latt_b": -0.654002606868744,
      "F_latt": 1.07852524234798
    },
    {
      "phi_tic": 2,
      "phi_deg": 0.0222222222222222,
      "k_frac": -0.593161582946777,
      "F_latt_b": -0.388755053281784,
      "F_latt": 0.671564671377393
    },
    {
      "phi_tic": 3,
      "phi_deg": 0.0333333333333333,
      "k_frac": -0.595171689987183,
      "F_latt_b": -0.0884189531207085,
      "F_latt": 0.159541734546532
    },
    {
      "phi_tic": 4,
      "phi_deg": 0.0444444444444444,
      "k_frac": -0.597181558609009,
      "F_latt_b": 0.220785543322563,
      "F_latt": -0.415164805287365
    },
    {
      "phi_tic": 5,
      "phi_deg": 0.0555555555555556,
      "k_frac": -0.599191427230835,
      "F_latt_b": 0.511898458003998,
      "F_latt": -1.00054741889294
    },
    {
      "phi_tic": 6,
      "phi_deg": 0.0666666666666667,
      "k_frac": -0.601201057434082,
      "F_latt_b": 0.759344637393951,
      "F_latt": -1.53945502474902
    },
    {
      "phi_tic": 7,
      "phi_deg": 0.0777777777777778,
      "k_frac": -0.60321044921875,
      "F_latt_b": 0.941327095031738,
      "F_latt": -1.97558293388473
    },
    {
      "phi_tic": 8,
      "phi_deg": 0.0888888888888889,
      "k_frac": -0.605220317840576,
      "F_latt_b": 1.04169797897339,
      "F_latt": -2.25921634449701
    },
    {
      "phi_tic": 9,
      "phi_deg": 0.1,
      "k_frac": -0.607229709625244,
      "F_latt_b": 1.05128383636475,
      "F_latt": -2.35148472430236
    }
  ]
}